botsay/Bots.py
botsay/__init__.py
botsay/main.py
botsay-0.1.0.dist-info/METADATA
botsay-0.1.0.dist-info/WHEEL
botsay-0.1.0.dist-info/entry_points.txt
botsay-0.1.0.dist-info/RECORD
